AUTHORS.rst
CHANGELOG.md
CONTRIBUTING.rst
LICENSE
README.rst
languages_plus/__init__.py
languages_plus/admin.py
languages_plus/apps.py
languages_plus/data/data.zip
languages_plus/fixtures/languages_data.json.gz
languages_plus/migrations/0001_initial.py
languages_plus/migrations/0002_auto_20141008_0947.py
languages_plus/migrations/0003_auto_20150803_1140.py
languages_plus/migrations/0004_auto_20171214_0004.py
languages_plus/migrations/__init__.py
languages_plus/models.py
languages_plus/utils.py
languages_plus/views.py
django_languages_plus-2.1.1.dist-info/LICENSE
django_languages_plus-2.1.1.dist-info/METADATA
django_languages_plus-2.1.1.dist-info/WHEEL
django_languages_plus-2.1.1.dist-info/RECORD
