Metadata-Version: 2.1
Name: django-languages-plus
Version: 2.1.1
Summary: A django model & fixture containing common languages and culture codes
Home-page: https://github.com/cordery/django-languages-plus
License: MIT
Keywords: django-languages-plus
Author: Andrew Cordery
Author-email: cordery@gmail.com
Requires-Python: >=3.8,<4
Classifier: Development Status :: 5 - Production/Stable
Classifier: Framework :: Django
Classifier: Framework :: Django :: 3.2
Classifier: Framework :: Django :: 4.2
Classifier: Framework :: Django :: 5.0
Classifier: Intended Audience :: Developers
Classifier: License :: OSI Approved :: MIT License
Classifier: Natural Language :: English
Classifier: Programming Language :: Python :: 3
Classifier: Programming Language :: Python :: 3.8
Classifier: Programming Language :: Python :: 3.9
Classifier: Programming Language :: Python :: 3.10
Classifier: Programming Language :: Python :: 3.11
Classifier: Programming Language :: Python :: 3.12
Requires-Dist: django (>=3.2,<6)
Requires-Dist: django-countries-plus (>2)
Project-URL: Repository, https://github.com/cordery/django-languages-plus
